{
    "name": "Multi-Hopper",
    "sortnum": 1,
    "icon": "hopperxtreme:multi_hopper",
    "category": "hopperxtreme:multi_hoppers",
    "read_by_default": true,
    "pages": [
        {
            "type": "patchouli:text",
            "text": "$(l)Cooldown$()$(br)8 game ticks (2.5 items / second)"
        },
        {
            "type": "patchouli:crafting",
            "recipe": "hopperxtreme:multi_hopper",
            "recipe2": "hopperxtreme:hopper_from_multi",
            "title": "Recipe"
        }
    ]
}
